Pysotopes/__init__.py
Pysotopes/pysotopes.py
Pysotopes/test.py
pysotopes-0.0.2.dist-info/METADATA
pysotopes-0.0.2.dist-info/WHEEL
pysotopes-0.0.2.dist-info/top_level.txt
pysotopes-0.0.2.dist-info/RECORD
