Metadata-Version: 2.4
Name: Pysotopes
Version: 0.0.2
Summary: A basic UI building library built on top on tkinter
Author: HapooIsLuv
Author-email: <Hapoo@gmail.com>
Keywords: python,UI,library
Classifier: Development Status :: 1 - Planning
Classifier: Intended Audience :: Developers
Classifier: Programming Language :: Python :: 3
Classifier: Operating System :: Unix
Classifier: Operating System :: MacOS :: MacOS X
Classifier: Operating System :: Microsoft :: Windows
Dynamic: author
Dynamic: author-email
Dynamic: classifier
Dynamic: keywords
Dynamic: summary
